Pyflai/__init__.py
Pyflai/test.py
Pyflai-0.0.1.dev3.dist-info/DESCRIPTION.rst
Pyflai-0.0.1.dev3.dist-info/METADATA
Pyflai-0.0.1.dev3.dist-info/RECORD
Pyflai-0.0.1.dev3.dist-info/WHEEL
Pyflai-0.0.1.dev3.dist-info/metadata.json
Pyflai-0.0.1.dev3.dist-info/top_level.txt
