Metadata-Version: 2.0
Name: Pyflai
Version: 0.0.1.dev3
Summary: A python design framework.
Home-page: UNKNOWN
Author: ArnyminerZ
Author-email: arnyminer.z@gmail.com
License: Apache-2.0
Platform: UNKNOWN
Requires-Python: >=3
Requires-Dist: pygame
Requires-Dist: webcolors
